{
  "parent": "minecraft:recipes/root",
  "criteria": {
    "has_the_recipe": {
      "conditions": {
        "recipe": "anvilcraft:creamy_bread_roll"
      },
      "trigger": "minecraft:recipe_unlocked"
    },
    "hasitem": {
      "conditions": {
        "items": [
          {
            "items": [
              "anvilcraft:cream"
            ]
          }
        ]
      },
      "trigger": "minecraft:inventory_changed"
    }
  },
  "requirements": [
    [
      "hasitem",
      "has_the_recipe"
    ]
  ],
  "rewards": {
    "recipes": [
      "anvilcraft:creamy_bread_roll"
    ]
  },
  "sends_telemetry_event": false
}