{
  "parent": "minecraft:recipes/root",
  "criteria": {
    "has_blade_of_the_sea": {
      "conditions": {
        "items": [
          {
            "items": [
              "anvilcraft:blade_of_the_sea"
            ]
          }
        ]
      },
      "trigger": "minecraft:inventory_changed"
    },
    "has_prismarine_shard": {
      "conditions": {
        "items": [
          {
            "items": [
              "minecraft:prismarine_shard"
            ]
          }
        ]
      },
      "trigger": "minecraft:inventory_changed"
    },
    "has_the_recipe": {
      "conditions": {
        "recipe": "minecraft:trident"
      },
      "trigger": "minecraft:recipe_unlocked"
    }
  },
  "requirements": [
    [
      "has_blade_of_the_sea",
      "has_prismarine_shard",
      "has_the_recipe"
    ]
  ],
  "rewards": {
    "recipes": [
      "minecraft:trident"
    ]
  },
  "sends_telemetry_event": false
}